chatairunner/__init__.py
chatairunner/base_window.py
chatairunner/chatbot.py
chatairunner/conversation.py
chatairunner/main.py
chatairunner/main_llm.py
chatairunner/prompt.py
chatairunner/settings_manager.py
chatairunner-1.0.10.dist-info/LICENSE
chatairunner-1.0.10.dist-info/METADATA
chatairunner-1.0.10.dist-info/WHEEL
chatairunner-1.0.10.dist-info/top_level.txt
chatairunner-1.0.10.dist-info/RECORD
