Metadata-Version: 2.1
Name: chatairunner
Version: 1.0.10
Summary: Chat AI: A chatbot framework
Home-page: https://github.com/Capsize-Games/chat-ai
Author: Capsize LLC
Author-email: contact@capsize.gg
License: AGPL-3.0
Keywords: ai,chatbot,chat,ai
Requires-Python: >=3.10.0
License-File: LICENSE
Requires-Dist: aihandler (==1.8.19)
